LICENSE
MANIFEST.in
README.rst
README.txt
setup.cfg
setup.py
docs/CHANGES.txt
spiny/__init__.py
spiny/environment.py
spiny/main.py
spiny/projectdata.py
spiny.egg-info/PKG-INFO
spiny.egg-info/SOURCES.txt
spiny.egg-info/dependency_links.txt
spiny.egg-info/entry_points.txt
spiny.egg-info/top_level.txt
spiny.egg-info/zip-safe
tests/__init__.py
tests/test_environment.py
tests/test_main.py
tests/utils.py
tests/configs/dual.conf
tests/configs/minimal.conf
tests/package/setup.py
tests/package/dinsdale/__init__.py
tests/package/tests/__init__.py