Metadata-Version: 1.1
Name: spiny
Version: 0.6
Summary: Spiny will run your Python tests under multiple versions of Python
Home-page: https://github.com/regebro/spiny/
Author: Lennart Regebro
Author-email: regebro@gmail.com
License: MIT
Keywords: development,tools,testing
Platform: UNKNOWN
Classifier: Development Status :: 4 - Beta
Classifier: Operating System :: Unix
Classifier: Programming Language :: Python
Classifier: Programming Language :: Python :: 3.4
Classifier: Programming Language :: Python :: 3.5
Classifier: Programming Language :: Python :: 3.6
Classifier: Topic :: Software Development :: Testing
